subdivisions/__init__.py
subdivisions/base.py
subdivisions/builders/__init__.py
subdivisions/builders/events.py
subdivisions/builders/sns.py
subdivisions/builders/sqs.py
subdivisions/check_versions.py
subdivisions/client.py
subdivisions/config.py
subdivisions/events.py
subdivisions/events_v2.py
subdivisions/exceptions.py
subdivisions/policies.py
subdivisions/utils.py
subdivisions-1.53.0.dist-info/WHEEL
subdivisions-1.53.0.dist-info/METADATA
subdivisions-1.53.0.dist-info/RECORD
