Metadata-Version: 2.1
Name: subdivisions
Version: 1.53.0
Summary: A55 AWS PubSub Library
Home-page: https://github.com/access55/subdivisions
License: GPL-3.0
Keywords: pubsub
Author: A55 Tech
Author-email: tech@a55.tech
Requires-Python: >=3.7,<4.0
Classifier: License :: OSI Approved :: GNU General Public License v3 (GPLv3)
Classifier: Programming Language :: Python :: 3
Classifier: Programming Language :: Python :: 3.10
Classifier: Programming Language :: Python :: 3.7
Classifier: Programming Language :: Python :: 3.8
Classifier: Programming Language :: Python :: 3.9
Requires-Dist: arrow
Requires-Dist: asbool
Requires-Dist: boto3
Requires-Dist: coverage
Requires-Dist: loguru
Requires-Dist: mypy
Requires-Dist: python-dotenv
Requires-Dist: stringcase
Project-URL: Repository, https://github.com/access55/subdivisions
